CHANGES.txt
LICENSE.txt
bootstrap.py
buildout.cfg
setup.py
src/lovely/__init__.py
src/lovely.mail.egg-info/PKG-INFO
src/lovely.mail.egg-info/SOURCES.txt
src/lovely.mail.egg-info/dependency_links.txt
src/lovely.mail.egg-info/namespace_packages.txt
src/lovely.mail.egg-info/not-zip-safe
src/lovely.mail.egg-info/requires.txt
src/lovely.mail.egg-info/top_level.txt
src/lovely/mail/LICENSE.txt
src/lovely/mail/README.txt
src/lovely/mail/SETUP.cfg
src/lovely/mail/__init__.py
src/lovely/mail/configure.zcml
src/lovely/mail/lovely.mail-configure.zcml
src/lovely/mail/remotemail.py
src/lovely/mail/remotemail.txt
src/lovely/mail/testing.py
src/lovely/mail/tests.py