Metadata-Version: 1.0
Name: lovely.mail
Version: 0.3.1
Summary: sending emails via remotetask
Home-page: http://launchpad.net/lovely.mail
Author: Lovely Systems
Author-email: office@lovelysystems.com
License: ZPL 2.1
Keywords: mail zope zope3
Platform: UNKNOWN
Classifier: Development Status :: 4 - Beta
Classifier: Intended Audience :: Developers
Classifier: License :: OSI Approved :: Zope Public License
Classifier: Topic :: Software Development :: Libraries :: Python Modules
